jieba_fast_dat/__init__.py
jieba_fast_dat/__main__.py
jieba_fast_dat/_jieba_fast_dat_functions_py3.cpython-312-x86_64-linux-gnu.so
jieba_fast_dat/dict.txt
jieba_fast_dat/utils.py
jieba_fast_dat/analyse/__init__.py
jieba_fast_dat/analyse/analyzer.py
jieba_fast_dat/analyse/idf.txt
jieba_fast_dat/analyse/textrank.py
jieba_fast_dat/analyse/tfidf.py
jieba_fast_dat/core/__init__.py
jieba_fast_dat/core/functions.py
jieba_fast_dat/core/tokenizer.py
jieba_fast_dat/finalseg/__init__.py
jieba_fast_dat/finalseg/prob_emit.p
jieba_fast_dat/finalseg/prob_emit.py
jieba_fast_dat/finalseg/prob_start.p
jieba_fast_dat/finalseg/prob_start.py
jieba_fast_dat/finalseg/prob_trans.p
jieba_fast_dat/finalseg/prob_trans.py
jieba_fast_dat/posseg/__init__.py
jieba_fast_dat/posseg/char_state_tab.p
jieba_fast_dat/posseg/char_state_tab.py
jieba_fast_dat/posseg/prob_emit.p
jieba_fast_dat/posseg/prob_emit.py
jieba_fast_dat/posseg/prob_start.p
jieba_fast_dat/posseg/prob_start.py
jieba_fast_dat/posseg/prob_trans.p
jieba_fast_dat/posseg/prob_trans.py
jieba_fast_dat/posseg/viterbi.py
jieba_fast_dat/source/cedarpp.h
jieba_fast_dat/source/pybind_bindings.cpp
jieba_fast_dat-0.58.dist-info/METADATA
jieba_fast_dat-0.58.dist-info/WHEEL
jieba_fast_dat-0.58.dist-info/top_level.txt
jieba_fast_dat-0.58.dist-info/RECORD
jieba_fast_dat-0.58.dist-info/licenses/LICENSE
