Metadata-Version: 2.4
Name: jieba_fast_dat
Version: 0.58
Summary: Use C++ and pybind11 to Speed up jieba<Chinese Words Segementation Utilities>
Author: Sun, Junyi, deepcs233, carycha
License-Expression: MIT
Project-URL: Homepage, https://github.com/carycha/jieba_fast_dat
Keywords: NLP,tokenizing,Chinese word segementation
Classifier: Intended Audience :: Developers
Classifier: Operating System :: OS Independent
Classifier: Natural Language :: Chinese (Simplified)
Classifier: Natural Language :: Chinese (Traditional)
Classifier: Programming Language :: Python
Classifier: Programming Language :: Python :: 3.10
Classifier: Programming Language :: Python :: 3.11
Classifier: Programming Language :: Python :: 3.12
Classifier: Topic :: Text Processing
Classifier: Topic :: Text Processing :: Indexing
Classifier: Topic :: Text Processing :: Linguistic
Requires-Python: >=3.10
License-File: LICENSE
Provides-Extra: dev
Requires-Dist: pytest; extra == "dev"
Requires-Dist: pytest-timeout; extra == "dev"
Requires-Dist: pytest-cov; extra == "dev"
Requires-Dist: uv; extra == "dev"
Requires-Dist: setuptools; extra == "dev"
Requires-Dist: build; extra == "dev"
Requires-Dist: pre-commit; extra == "dev"
Requires-Dist: whoosh; extra == "dev"
Requires-Dist: pybind11; extra == "dev"
Requires-Dist: scikit-learn; extra == "dev"
Requires-Dist: ruff; extra == "dev"
Requires-Dist: twine; extra == "dev"
Requires-Dist: auditwheel; extra == "dev"
Requires-Dist: jieba; extra == "dev"
Requires-Dist: pyright; extra == "dev"
Requires-Dist: types-setuptools; extra == "dev"
Requires-Dist: psutil; extra == "dev"
Dynamic: license-file
